x_cloud_py
