Metadata-Version: 1.1
Name: xCloudPy
Version: 0.3.0
Summary: Public cloud libs basic wrapper
Home-page: https://github.com/wankes2000/xCloudPy
Author: Arturo Martinez
Author-email: wankes2000@gmail.com
License: UNKNOWN
Download-URL: https://github.com/wankes2000/xCloudPy/archive/0.3.0.tar.gz
Keywords: aws,cloud,google,gcp
Platform: UNKNOWN
